tm1637.py
rpi_tm1637-1.3.4.dist-info/LICENSE.txt
rpi_tm1637-1.3.4.dist-info/METADATA
rpi_tm1637-1.3.4.dist-info/WHEEL
rpi_tm1637-1.3.4.dist-info/top_level.txt
rpi_tm1637-1.3.4.dist-info/RECORD
