Metadata-Version: 2.1
Name: rpi-tm1637
Version: 1.3.4
Summary: Raspberry Pi Python port from MicroPython library for TM1637 LED driver.
Home-page: https://gitlab.com/lookslikematrix/rpi-tm1637
Author: Mike Causer
Author-email: mcauser@gmail.com
Maintainer: Christian Decker
Maintainer-email: christian.decker@lookslikematrix.de
License: MIT
Keywords: tm1637 raspberry pi seven segment led python
Platform: UNKNOWN
Classifier: Programming Language :: Python :: 3
Classifier: Development Status :: 5 - Production/Stable
Classifier: License :: OSI Approved :: MIT License
Requires-Python: >=3
License-File: LICENSE.txt
Requires-Dist: wiringpi
